CHANGES.rst
LICENSE.rst
MANIFEST.in
README.rst
requirements.txt
requirements_dev.txt
setup.py
docs/api_reference.rst
docs/authors.rst
docs/changes.rst
docs/contribute.rst
docs/index.rst
docs/install.rst
docs/transfer_syntax.rst
docs/tutorial.rst
docs/upcoming.rst
mudicom/__init__.py
mudicom/base.py
mudicom/exceptions.py
mudicom/image.py
mudicom/lookup.py
mudicom/validation.py
mudicom.egg-info/PKG-INFO
mudicom.egg-info/SOURCES.txt
mudicom.egg-info/dependency_links.txt
mudicom.egg-info/requires.txt
mudicom.egg-info/top_level.txt
mudicom/tests/__init__.py
mudicom/tests/test_image.py
mudicom/tests/test_read.py
mudicom/tests/test_validate.py