Metadata-Version: 1.1
Name: mudicom
Version: 0.1.2
Summary: Read, validate, anonymize, and extract images from a DICOM file using GDCM
Home-page: https://github.com/neurosnap/mudicom
Author: Eric Bower
Author-email: neurosnap@gmail.com
License: The MIT License
